{
  "kind": "collectionType",
  "collectionName": "templates",
  "info": {
    "singularName": "template",
    "pluralName": "templates",
    "displayName": "Template",
    "description": ""
  },
  "options": {
    "draftAndPublish": false
  },
  "pluginOptions": {},
  "attributes": {
    "name": {
      "type": "string"
    },
    "siteLayout": {
      "type": "relation",
      "relation": "oneToOne",
      "target": "api::block.block"
    },
    "pageLayout": {
      "type": "relation",
      "relation": "oneToOne",
      "target": "api::block.block"
    }
  }
}
